kenu_ai/__init__.py
kenu_ai-0.2.7.dist-info/METADATA
kenu_ai-0.2.7.dist-info/WHEEL
kenu_ai-0.2.7.dist-info/top_level.txt
kenu_ai-0.2.7.dist-info/RECORD
