Metadata-Version: 2.1
Name: kenu-ai
Version: 0.2.7
Summary: Python Chat AI
Author: r4isy
Author-email: r4isy@kenucorp.com
Requires-Dist: googletrans (==4.0.0-rc1)
Requires-Dist: requests
Requires-Dist: kufpy
